[{
        "name": "Travel",
        "icon": ""
    },
    {
        "name": "Petrol",
        "icon": ""
    },
    {
        "name": "Medic",
        "icon": ""
    },
    {
        "name": "lunch",
        "icon": ""
    }, {
        "name": "Dinner",
        "icon": ""
    },
    {
        "name": "Smoking",
        "icon": ""
    },
    {
        "name": "Misc",
        "icon": ""
    },
    {
        "name": "Misc 2",
        "icon": ""
    },
    {
        "name": "Misc 3",
        "icon": ""
    },
    {
        "name": "Misc 4",
        "icon": ""
    },
    {
        "name": "Misc 5",
        "icon": ""
    },
    {
        "name": "Misc 6",
        "icon": ""
    }

]